{"cameraMode":{"drawMode":0,"name":"Shaded","section":"Shading Mode"},"sceneLighting":true,"audioPlay":false,"sceneViewState":{"m_AlwaysRefresh":false,"showFog":true,"showSkybox":true,"showFlares":true,"showImageEffects":true,"showParticleSystems":true,"showVisualEffectGraphs":true,"m_FxEnabled":true},"in2DMode":false,"pivot":{"x":2.737650156021118,"y":-20.769662857055665,"z":-0.16675692796707154},"rotation":{"x":0.3475296199321747,"y":-0.6445128917694092,"z":0.4211653769016266,"w":0.5383720397949219},"size":20.798595428466798,"orthographic":false}